### 1. Java基本数据类型

-    1.1. Java语言有8种基本数据类型
·


        基本数据类型包括如下：boolean、byte、short、int、long、float、double和char。
        详细划分为：
        整数类型：byte、short、int、long；
        浮点类型：float、double；
        逻辑类型：boolean；
        字符类型：char;
 
-    1.2. 详细介绍
·

    1.2.1. 整数类型
        Java各数据类型有固定的表数范围和字段长度，其不受操作系统影响，保证了Java的可移植性。
        类型 占存储空间 表数范围
        byte 1字节 -128~127
        short 2字节 215~215-1
        int 4字节 231~231-1
        long 8字节 263~263-1
        表格中byte为27-1，1个字节8位，包含一个符号位所以是7次方，-1是因为包含0。
             
        整型常量的三种表示形式：
        十进制数，如：12，-555，0；
        八进制数，要求以0开头，如：012；
        十六进制数，要求以0x或者0X开头，如：0x12。
        Java语言的整型常量默认是int类型，声明long类型时需要在结尾加l或者L：
        long l1 = 8L;//结尾必须加L或者l

·

    1.2.2 浮点类型
        Java浮点类型有固定的表数范围和字段长度，其不受操作系统影响，保证了Java的可移植性。
        类型 占存储空间 表数范围
        float 4字节 -3.403E38~3.403E38
        double 8字节 -17.98E308~17.98E308
        浮点数在现实中是连续的，在计算机数据结构中是离散的，计算机内部表示浮点数是有误差的。
        float保留8位有效数字，小数点后前7位是精确的；
        double保留16位有效数字，小数点后15位是精确的。
         
        浮点型常量的三种表示形式：
        十进制形式，如：3.14，314.0，.314；
        科学计数法形式，如：3.14e2，3.24E2，100E-2。
        Java语言的浮点型常量默认是double类型，声明float类型时需要在结尾加f或者F：
        float f = 1.03f;//结尾必须加F或者f
·
 
    1.2.3 逻辑类型
        boolean类型数据只允许取值true或false，不能用0或者非0整数代替true和false。
        boolean的内存占用大小的问题，出于好奇去网上找了找相关资料：
        This data type represents one bit of information（这种数据类型代表一个比特的信息）
        its "size" isn't something that's precisely defined.（它的大小没有明确界定）
        即使一个bit 就能用，最小的内存寻址单元就是byte,所以占用一个byte。        
·

    1.2.4 字符类型
        对于char类型变量表示通常意义上的字符，内存中分配给2个字节，占16位。char类型变量的取值范围是0~65535。Java采用Unicode编码，因而可以使用16进制编码形式表示。
        char character = '\u0061';
        System.out.println(character);
        输出结果：a
        
       
| 类型      | 型别  | 字节    | 取值范围                              |
|---------|-----|-------|-----------------------------------|
| byte    | 整型  | 1byte | \-27 ~ 27\-1
                     |
| short   | 整型  | 2byte | \-215 ~ 215\-1                    |
| int     | 整型  | 4byte | \-231 ~ 231\-1                    |
| long    | 整型  | 8byte | \-263 ~ 263\-1                    |
| float   | 浮点型 | 4byte | 3\.402823e\+38 ~ 1\.401298e\-45   |
| double  | 浮点型 | 8byte | 1\.797693e\+308~ 4\.9000000e\-324 |
| char    | 文本型 | 2byte | 0~216\-1                          |
| boolean | 布尔型 | 1byte | true/false                        |

#### 2. Java拆装箱
目录:\
　　2.1. 什么是装箱？什么是拆箱？ \
　　2.2. 实现原理 \
　　2.2. 面试中相关的问题 

·

    2.1.什么是装箱？什么是拆箱？
        装箱:自动将基本数据类型转换为包装器类型
        拆箱:自动将包装器类型转换为基本数据类型
        
        在Java SE5之前，如果要生成一个数值为10的Integer对象，必须这样进行：Integer i = new Integer(10);
        而在从Java SE5开始就提供了自动装箱的特性，如果要生成一个数值为10的Integer对象，只需要这样就可以了：Integer i = 10;
        这个过程中会自动根据数值创建对应的 Integer对象，这就是装箱。
        那什么是拆箱呢？顾名思义，跟装箱对应，就是自动将包装器类型转换为基本数据类型：
        Integer i = 10;  //装箱
        int n = i;   //拆箱
    
        基本数据类型对应的包装器类型：
        int（4字节） Integer
        byte（1字节） Byte
        short（2字节） Short
        long（8字节） Long
        float（4字节） Float
        double（8字节） Double
        char（2字节） Character
        boolean（未定） Boolean
·

    2.2 装箱和拆箱是如何实现的
        上一小节了解装箱的基本概念之后，这一小节来了解一下装箱和拆箱是如何实现的。
        我们就以Interger类为例，下面看一段代码：
        源
        public class IntegerIntTest {
            public static void main(String[] args) {
                Integer i = 10;
                int n = i;
            }
        }
```
反编译:

public class IntegerIntTest
  minor version: 0
  major version: 52
  flags: ACC_PUBLIC, ACC_SUPER
{
  public IntegerIntTest();
    descriptor: ()V
    flags: ACC_PUBLIC
    Code:
      stack=1, locals=1, args_size=1
         0: aload_0
         1: invokespecial #1                  // Method java/lang/Object."<init>":()V
         4: return
      LineNumberTable:
        line 1: 0
      LocalVariableTable:
        Start  Length  Slot  Name   Signature
            0       5     0  this   LIntegerIntTest;

  public static void main(java.lang.String[]);
    descriptor: ([Ljava/lang/String;)V
    flags: ACC_PUBLIC, ACC_STATIC
    Code:
      stack=1, locals=3, args_size=1
         0: bipush        10
         2: invokestatic  #2                  // Method java/lang/Integer.valueOf:(I)Ljava/lang/Integer;
         5: astore_1
         6: aload_1
         7: invokevirtual #3                  // Method java/lang/Integer.intValue:()I
        10: istore_2
        11: return
      LineNumberTable:
        line 3: 0
        line 4: 6
        line 5: 11
      LocalVariableTable:
        Start  Length  Slot  Name   Signature
            0      12     0  args   [Ljava/lang/String;
            6       6     1     i   Ljava/lang/Integer;
           11       1     2     n   I
}
```
        从反编译得到的字节码内容可以看出，在装箱的时候自动调用的是Integer的valueOf(int)方法。而在拆箱的时候自动调用的是Integer的intValue方法。
        其他的也类似，比如Double、Character，不相信的朋友可以自己手动尝试一下。
        因此可以用一句话总结装箱和拆箱的实现过程：
        装箱过程是通过调用包装器的valueOf方法实现的，而拆箱过程是通过调用包装器的 xxxValue方法实现的。（xxx代表对应的基本数据类型）。
- 2.3. 基本类型封装类Cache缓存

         测试：
         public static void main(String[] args) {
             testCache(true);
             testCache(false);
         }
     
         public static void testCache(boolean outCache){
             int testi;
             if (outCache){
                 System.out.println("out cache");
                 testi = 516;
             } else {
                 testi = 12;
                 System.out.println("in cache");
             }
     
             Integer ito1 = testi;
             int it = ito1;
             Integer ito2 = it;
             System.out.print("object == basic ");
             System.out.println(ito1 == it);
             System.out.print("object equals basic ");
             System.out.println(ito1.equals(it));
             System.out.print("object == object ");
             System.out.println(ito1 == ito2);
             System.out.print("object equals object ");
             System.out.println(ito1.equals(ito2));
         }
         输出
         out cache
         object == basic true
         object equals basic true
         object == object false
         object equals object true
         in cache
         object == basic true
         object equals basic true
         object == object true
         object equals object true
     
 ·
 
         原因介绍：    
         byte Byte(ByteCache) 
             public static Byte valueOf(byte b) {
                     final int offset = 128;
                     return ByteCache.cache[(int)b + offset];
             }
         所有Byte类型全部缓存
· 
        
         short Short(ShortCache)
             public static Short valueOf(short s) {
                 final int offset = 128;
                 int sAsInt = s;
                 if (sAsInt >= -128 && sAsInt <= 127) { // must cache
                     return ShortCache.cache[sAsInt + offset];
                 }
                 return new Short(s);
             }
         Short类型 -128~127为缓存对象（==，equals相等），其他equals相等
·
        
         int Integer (IntegerCache)
             public static Integer valueOf(int i) {
                 // final int low = -128;
                 // final int high = 127;
                 if (i >= IntegerCache.low && i <= IntegerCache.high)
                     return IntegerCache.cache[i + (-IntegerCache.low)];
                 return new Integer(i);
             }
         Integer类型 -128~127为缓存对象（==，equals相等），其他equals相等
·
         
         long Long (LongCache)
             public static Long valueOf(long l) {
                 final int offset = 128;
                 if (l >= -128 && l <= 127) { // will cache
                     return LongCache.cache[(int)l + offset];
                 }
                 return new Long(l);
             }
         Long类型 -128~127为缓存对象（==，equals相等），其他equals相等
·
    
         char Character (CharacterCache)
             public static Character valueOf(char c) {
                 if (c <= 127) { // must cache
                     return CharacterCache.cache[(int)c];
                 }
                 return new Character(c);
           }
        
         Character类型 小于127为缓存对象（==，equals相等），其他equals相等
·
              
         float Float
             public static Float valueOf(float f) {
                 return new Float(f);
             }
         无缓存
·
         
         double Double
             public static Double valueOf(double d) {
                 return new Double(d);
             }
         无缓存
·
        
         boolean Boolean
            public static Boolean valueOf(boolean b) {
                return (b ? TRUE : FALSE);
            }
         就两个值不需要缓存

参考：
https://www.jianshu.com/p/547b36f04239
http://www.cnblogs.com/dolphin0520/p/3780005.html
